sagellm_compression/__init__.py
sagellm_compression/__init__.pyc
sagellm_compression/__pycache__/__init__.cpython-311.pyc
sagellm_compression/cot/__init__.py
sagellm_compression/cot/__init__.pyc
sagellm_compression/cot/templates.pyc
isagellm_compression-0.4.0.10.dist-info/METADATA
isagellm_compression-0.4.0.10.dist-info/WHEEL
isagellm_compression-0.4.0.10.dist-info/top_level.txt
isagellm_compression-0.4.0.10.dist-info/RECORD
