Metadata-Version: 2.4
Name: isagellm-compression
Version: 0.4.0.10
Summary: Model Compression & Acceleration Module for sageLLM
Author-email: IntelliStream Team <shuhao_zhang@hust.edu.cn>
License: Private
Project-URL: Homepage, https://github.com/intellistream/sagellm-compression
Project-URL: Repository, https://github.com/intellistream/sagellm-compression
Project-URL: Issues, https://github.com/intellistream/sagellm-compression/issues
Keywords: llm,inference,quantization,sparsity,compression,domestic-hardware
Classifier: Development Status :: 3 - Alpha
Classifier: Intended Audience :: Developers
Classifier: Programming Language :: Python :: 3.10
Classifier: Programming Language :: Python :: 3.11
Requires-Python: ==3.11.*
Requires-Dist: isagellm-protocol<0.5.0,>=0.4.0.0
Requires-Dist: isagellm-backend<0.5.0,>=0.4.0.0
Requires-Dist: pydantic>=2.0.0
Provides-Extra: dev
Requires-Dist: pytest>=7.0.0; extra == "dev"
Requires-Dist: pytest-cov>=4.0.0; extra == "dev"
Requires-Dist: mypy>=1.0.0; extra == "dev"
Requires-Dist: ruff>=0.1.0; extra == "dev"
Requires-Dist: isage-pypi-publisher>=0.2.0; extra == "dev"
